django_iubenda/__init__.py
django_iubenda_web-0.0.4.dist-info/LICENSE
django_iubenda_web-0.0.4.dist-info/METADATA
django_iubenda_web-0.0.4.dist-info/WHEEL
django_iubenda_web-0.0.4.dist-info/top_level.txt
django_iubenda_web-0.0.4.dist-info/RECORD
